[
  {
    "id": "application",
    "class": "bitbetrieb\\CMS\\Application\\Application",
    "type": "singleton",
    "dependencies": [
      "front-controller"
    ]
  },
  {
    "id": "front-controller",
    "class": "bitbetrieb\\CMS\\FrontController\\FrontController",
    "type": "singleton",
    "dependencies": [
      "request",
      "response",
      "routes-php"
    ]
  },
  {
    "id": "request",
    "class": "bitbetrieb\\CMS\\HTTP\\Request",
    "type": "singleton",
    "dependencies": []
  },
  {
    "id": "response",
    "class": "bitbetrieb\\CMS\\HTTP\\Response",
    "type": "singleton",
    "dependencies": []
  },
  {
    "id": "routes-php",
    "value": "../app/routes.php",
    "type": "value"
  },
  {
    "id": "config",
    "class": "bitbetrieb\\CMS\\Config\\Config",
    "type": "singleton",
    "dependencies": [
      "config-file"
    ]
  },
  {
    "id": "config-file",
    "value": "../config/config.json",
    "type": "value"
  },
  {
    "id": "controller-namespace",
    "value": "\\bitbetrieb\\CMS\\Controller\\",
    "type": "value"
  },
  {
    "id": "models-namespace",
    "value": "\\bitbetrieb\\CMS\\Model\\",
    "type": "value"
  }
]
